{
    "current_version": "0.3.11.0",
    "update_url": "https://raw.githubusercontent.com/Alexandr-Botovod/Prison_Helper/refs/heads/main/PrisonHelper.lua",
    "update_info": "v0.0.4 - Снижение доступа к команде /givewbook\nv0.0.5 - Удалил лишние команды(/55, /66, /pnv, /irv) Часть 1\nv0.0.6 - Удаление лишних команд(/pas, /doc, /ts, /pr, /su, /fsu, /givefsu, /unsu, /clear, /frl, /fr, /inc, /ej, \n /pl, /mr/arr, /drugs, /rbomb, /delo, /dismiss) Часть 2\nv0.1.6 - Удалено УК и АК кодексы, сделанА функция включения/отключения авто-доклада в рацию\nv0.1.7 - Сделана функция отключения/включения авто-маски а также удалены лишние функции\nv0.2.7 - Обновлено оформление, добавлена новая вкладка в командах для Ст.Состава, удалён лишний код и т.д\nv.0.2.8 - Удаление лишнего кода, исправлены ошибки с прошлых версий\nv0.2.9 - Добавил никнейм VIP пользователя\nv0.2.10 - Добавил пункт состояние поста а также изменил код на доклад, фикс 4-го аргумента\n0.3.10 - Исправлено большое количество багов, добавлена вкладка функции",
    "news": [
      {
        "title": "Обновление #0.3.10.0",
        "date": "от 13.12.2024",
        "text": [
          "Исправил ошибку вкладки Команды для 5+ когда команды не редактировались",
          "Восстановил функцию РП отыгровок оружия",
          "Исправил поиск команд среди 3-ёх списков",
          "Сделал автоматическую регистрацию команд из вкладки Команды для 5+",
          "Добавлена вкладка Функции",
          "Добавлена рабочая статистика из /jobprogress"
        ]
      },
      {
        "title": "Обновление #0.3.11.0",
        "date": "от 15.12.2024",
        "text": ["Добавлена вкладка обновления"]
      }
    ]
  }
  